git_shield/__init__.py
git_shield/cli.py
git_shield/config.py
git_shield/entropy.py
git_shield/reporter.py
git_shield/scanner.py
git_shield/utils.py
git_shield-1.2.0.dist-info/METADATA
git_shield-1.2.0.dist-info/WHEEL
git_shield-1.2.0.dist-info/entry_points.txt
git_shield-1.2.0.dist-info/licenses/LICENSE
git_shield-1.2.0.dist-info/RECORD
