Metadata-Version: 2.4
Name: git-shield
Version: 1.2.0
Summary: Advanced secret detection for Git repositories
Author-email: Vamil Porwal <vamililporwal@gmail.com>
License: MIT
License-File: LICENSE
Keywords: cli,detection,git,secrets,security
Classifier: Development Status :: 4 - Beta
Classifier: Intended Audience :: Developers
Classifier: License :: OSI Approved :: MIT License
Classifier: Operating System :: OS Independent
Classifier: Programming Language :: Python :: 3
Classifier: Programming Language :: Python :: 3.8
Classifier: Programming Language :: Python :: 3.9
Classifier: Programming Language :: Python :: 3.10
Classifier: Programming Language :: Python :: 3.11
Classifier: Programming Language :: Python :: 3.12
Classifier: Topic :: Security
Classifier: Topic :: Software Development :: Quality Assurance
Requires-Python: >=3.8
Requires-Dist: click>=8.0.0
